[
  {
    "vocab_index": 376,
    "word": "རིང་པོ",
    "gloss": "Long",
    "sentences": [
      {
        "target": "ལམ་དེ་རིང་པོ་རེད།",
        "text": "That road is long."
      },
      {
        "target": "ངའི་སྐྲ་རིང་པོ་ཡོད།",
        "text": "My hair is long."
      },
      {
        "target": "ཁོང་གིས་ཡི་གེ་རིང་པོ་བྲིས།",
        "text": "He wrote a long letter."
      }
    ]
  },
  {
    "vocab_index": 377,
    "word": "དཔྱིད་ཀ",
    "gloss": "Spring",
    "sentences": [
      {
        "target": "དཔྱིད་ཀ་མེ་ཏོག་མང་པོ་སྐྱེ་གི་རེད།",
        "text": "In spring, many flowers grow."
      },
      {
        "target": "དཔྱིད་ཀ་གནམ་གཤིས་དྲོ་པོ་རེད།",
        "text": "The weather is warm in spring."
      },
      {
        "target": "ང་དཔྱིད་ཀ་རི་ལ་འགྲོ་གི་ཡིན།",
        "text": "I will go to the mountains in spring."
      }
    ]
  },
  {
    "vocab_index": 378,
    "word": "ནམ་མཁའ",
    "gloss": "Sky",
    "sentences": [
      {
        "target": "དེ་རིང་ནམ་མཁའ་སྔོན་པོ་རེད།",
        "text": "The sky is blue today."
      },
      {
        "target": "ནམ་མཁའ་ལ་སྤྲིན་པ་མང་པོ་འདུག",
        "text": "There are many clouds in the sky."
      },
      {
        "target": "མཚན་མོ་ནམ་མཁའ་ལ་སྐར་མ་འདུག",
        "text": "At night there are stars in the sky."
      }
    ]
  },
  {
    "vocab_index": 379,
    "word": "ཕོར་པ",
    "gloss": "Bowl",
    "sentences": [
      {
        "target": "ཕོར་པ་ནང་ལ་ཐུག་པ་འདུག",
        "text": "There is noodle soup in the bowl."
      },
      {
        "target": "ཨ་མས་ཕོར་པ་གཙང་མ་བཀྲུས།",
        "text": "Mother washed the bowl clean."
      },
      {
        "target": "ངས་ཇ་ཕོར་པ་གཅིག་འཐུང་།",
        "text": "I drank one bowl of tea."
      }
    ]
  },
  {
    "vocab_index": 380,
    "word": "མི",
    "gloss": "Human, person",
    "sentences": [
      {
        "target": "སྒོ་འགྲམ་ལ་མི་གཅིག་འདུག",
        "text": "There is one person by the door."
      },
      {
        "target": "ཁོ་མི་བཟང་པོ་རེད།",
        "text": "He is a good person."
      },
      {
        "target": "ཁྲོམ་ལ་མི་མང་པོ་འདུག",
        "text": "There are many people at the market."
      }
    ]
  },
  {
    "vocab_index": 381,
    "word": "གངས་ཆེན་པོ་འབབ",
    "gloss": "To snow heavily",
    "sentences": [
      {
        "target": "དེ་རིང་རི་ལ་གངས་ཆེན་པོ་འབབ་ཀྱི་འདུག",
        "text": "It is snowing heavily in the mountains today."
      },
      {
        "target": "མཚན་མོ་གངས་ཆེན་པོ་འབབ་སོང་།",
        "text": "It snowed heavily at night."
      },
      {
        "target": "གངས་ཆེན་པོ་འབབ་ན་ང་ཕྱི་ལ་མི་འགྲོ",
        "text": "If it snows heavily, I will not go outside."
      }
    ]
  },
  {
    "vocab_index": 382,
    "word": "ས་ཆ",
    "gloss": "Place",
    "sentences": [
      {
        "target": "ས་ཆ་འདི་ཞི་བདེ་རེད།",
        "text": "This place is peaceful."
      },
      {
        "target": "ང་ཚོས་ས་ཆ་གསར་པ་མཐོང་།",
        "text": "We saw a new place."
      },
      {
        "target": "ཁྱེད་རང་ག་པའི་ས་ཆ་ལ་བསྡད་ཡོད།",
        "text": "What place do you live in?"
      }
    ]
  },
  {
    "vocab_index": 383,
    "word": "རྔུལ་ནག་ཐོན",
    "gloss": "To sweat",
    "sentences": [
      {
        "target": "ཁོ་རྒྱུག་ནས་རྔུལ་ནག་ཐོན་སོང་།",
        "text": "He ran and started sweating."
      },
      {
        "target": "ཉི་མ་ཚ་པོ་ཡིན་དུས་ང་ལ་རྔུལ་ནག་ཐོན་གི་འདུག",
        "text": "When the sun is hot, I sweat."
      },
      {
        "target": "ལས་ཀ་མང་པོ་བྱས་ནས་ཁོ་མོར་རྔུལ་ནག་ཐོན་སོང་།",
        "text": "She sweated after doing a lot of work."
      }
    ]
  },
  {
    "vocab_index": 384,
    "word": "གཅིག་བྱས་ན",
    "gloss": "Maybe",
    "sentences": [
      {
        "target": "གཅིག་བྱས་ན་སང་ཉིན་ཆར་པ་འབབ་ཀྱི་རེད།",
        "text": "Maybe it will rain tomorrow."
      },
      {
        "target": "གཅིག་བྱས་ན་ཁོང་ཁྱིམ་ལ་ཡོད་ཀྱི་རེད།",
        "text": "Maybe he is at home."
      },
      {
        "target": "གཅིག་བྱས་ན་ང་ཚོ་དགོང་དྲོ་ཐུག་ཐུབ།",
        "text": "Maybe we can meet this evening."
      }
    ]
  },
  {
    "vocab_index": 385,
    "word": "འཁྱེར",
    "gloss": "To bring, carry",
    "sentences": [
      {
        "target": "ཁྱེད་རང་ཆར་གདུགས་འཁྱེར་དགོས།",
        "text": "You need to bring an umbrella."
      },
      {
        "target": "ངས་དེབ་གཉིས་འཁྱེར་ཡོད།",
        "text": "I am carrying two books."
      },
      {
        "target": "ཨ་ཕས་ཁུག་མ་ཆེན་པོ་འཁྱེར་སོང་།",
        "text": "Father carried a big bag."
      }
    ]
  },
  {
    "vocab_index": 386,
    "word": "ཆར་གདུགས",
    "gloss": "Umbrella",
    "sentences": [
      {
        "target": "ཆར་པ་འབབ་དུས་ཆར་གདུགས་དགོས།",
        "text": "When it rains, an umbrella is needed."
      },
      {
        "target": "ངའི་ཆར་གདུགས་དམར་པོ་རེད།",
        "text": "My umbrella is red."
      },
      {
        "target": "ཁོ་མོས་ཆར་གདུགས་གསར་པ་ཉོས།",
        "text": "She bought a new umbrella."
      }
    ]
  },
  {
    "vocab_index": 387,
    "word": "ཕྱི་པོ་ཆགས",
    "gloss": "To be late",
    "sentences": [
      {
        "target": "དེ་རིང་ང་འཛིན་གྲྭ་ལ་ཕྱི་པོ་ཆགས་སོང་།",
        "text": "I was late to class today."
      },
      {
        "target": "ཁོང་ལས་ཀ་ལ་ཕྱི་པོ་ཆགས་མ་སོང་།",
        "text": "He was not late to work."
      },
      {
        "target": "ཆར་པ་འབབ་ནས་ང་ཚོ་ཕྱི་པོ་ཆགས་སོང་།",
        "text": "Because it rained, we were late."
      }
    ]
  },
  {
    "vocab_index": 388,
    "word": "དུས་ཚོད་རག",
    "gloss": "To get the time",
    "sentences": [
      {
        "target": "དེ་རིང་ང་ལ་ཀློག་པའི་དུས་ཚོད་རག་སོང་།",
        "text": "Today I got time to read."
      },
      {
        "target": "ཁོ་མོར་ཇ་འཐུང་བའི་དུས་ཚོད་རག་མ་སོང་།",
        "text": "She did not get time to drink tea."
      },
      {
        "target": "གཟའ་མཇུག་ལ་ང་ཚོར་འཆམ་འཆམ་གྱི་དུས་ཚོད་རག་གི་རེད།",
        "text": "On the weekend we will get time for a walk."
      }
    ]
  },
  {
    "vocab_index": 389,
    "word": "བདུན་ཕྲག་སྔོན་མ",
    "gloss": "Last week",
    "sentences": [
      {
        "target": "བདུན་ཕྲག་སྔོན་མ་ང་ལྷ་ས་ལ་ཕྱིན་པ་ཡིན།",
        "text": "Last week I went to Lhasa."
      },
      {
        "target": "བདུན་ཕྲག་སྔོན་མ་ཁོང་གིས་དེབ་གསར་པ་ཉོས།",
        "text": "Last week he bought a new book."
      },
      {
        "target": "བདུན་ཕྲག་སྔོན་མ་གནམ་གཤིས་གྲང་མོ་རེད།",
        "text": "Last week the weather was cold."
      }
    ]
  },
  {
    "vocab_index": 390,
    "word": "ལྟད་མོ་ཆེན་པོ",
    "gloss": "Pleasant to watch",
    "sentences": [
      {
        "target": "ཞབས་བྲོ་དེ་ལྟད་མོ་ཆེན་པོ་འདུག",
        "text": "That dance is very nice to watch."
      },
      {
        "target": "དེ་རིང་རྟ་རྒྱུག་ལྟད་མོ་ཆེན་པོ་རེད།",
        "text": "Today the horse race is exciting to watch."
      },
      {
        "target": "ཁོང་གི་གློག་བརྙན་ལྟད་མོ་ཆེན་པོ་རེད།",
        "text": "His movie is very enjoyable to watch."
      }
    ]
  },
  {
    "vocab_index": 391,
    "word": "ནམ་དུས",
    "gloss": "Season",
    "sentences": [
      {
        "target": "ཁྱེད་རང་ནམ་དུས་གང་ལ་དགའ།",
        "text": "Which season do you like?"
      },
      {
        "target": "དཔྱིད་ཀ་ནམ་དུས་ཡག་པོ་རེད།",
        "text": "Spring is a good season."
      },
      {
        "target": "ནམ་དུས་འདི་ལ་ཆར་པ་མང་པོ་འབབ།",
        "text": "In this season, it rains a lot."
      }
    ]
  },
  {
    "vocab_index": 392,
    "word": "ལྷོ",
    "gloss": "South",
    "sentences": [
      {
        "target": "ལྷོ་ཕྱོགས་ལ་གནམ་གཤིས་དྲོ་པོ་རེད།",
        "text": "In the south, the weather is warm."
      },
      {
        "target": "ང་ཚོ་ལྷོ་ལ་འགྲོ་གི་ཡིན།",
        "text": "We will go south."
      },
      {
        "target": "ཁོང་གི་ཁང་པ་གྲོང་ཁྱེར་གྱི་ལྷོ་ལ་ཡོད།",
        "text": "His house is in the south of the city."
      }
    ]
  },
  {
    "vocab_index": 393,
    "word": "ནུབ",
    "gloss": "West",
    "sentences": [
      {
        "target": "ཉི་མ་ནུབ་ལ་འགྲོ་གི་འདུག",
        "text": "The sun is going down in the west."
      },
      {
        "target": "ཁྲོམ་དེ་གྲོང་གི་ནུབ་ལ་ཡོད།",
        "text": "That market is west of the village."
      },
      {
        "target": "ང་ནུབ་ཕྱོགས་ནས་ཡོང་བ་ཡིན།",
        "text": "I came from the west."
      }
    ]
  },
  {
    "vocab_index": 394,
    "word": "ཤར",
    "gloss": "East",
    "sentences": [
      {
        "target": "ཞོགས་པ་ཉི་མ་ཤར་ནས་འཆར།",
        "text": "In the morning the sun rises in the east."
      },
      {
        "target": "སློབ་གྲྭ་དེ་གྲོང་གི་ཤར་ལ་ཡོད།",
        "text": "That school is east of the village."
      },
      {
        "target": "ཁོ་ཤར་ཕྱོགས་ལ་ཕྱིན་སོང་།",
        "text": "He went toward the east."
      }
    ]
  },
  {
    "vocab_index": 395,
    "word": "བྱང",
    "gloss": "North",
    "sentences": [
      {
        "target": "བྱང་ཕྱོགས་ལ་གངས་མང་པོ་འབབ།",
        "text": "A lot of snow falls in the north."
      },
      {
        "target": "ངའི་གྲོགས་པོ་བྱང་ནས་ཡོང་།",
        "text": "My friend comes from the north."
      },
      {
        "target": "མཚོ་དེ་ཁང་པའི་བྱང་ལ་ཡོད།",
        "text": "The lake is north of the house."
      }
    ]
  },
  {
    "vocab_index": 396,
    "word": "མཚན་མོ",
    "gloss": "Night",
    "sentences": [
      {
        "target": "མཚན་མོ་ང་སྔ་པོ་གཉིད་ཁུག་གི་ཡོད།",
        "text": "At night I fall asleep early."
      },
      {
        "target": "མཚན་མོ་ཕྱི་ལ་ལྷགས་པ་ཆེན་པོ་འདུག",
        "text": "At night there is strong wind outside."
      },
      {
        "target": "ཁོ་མོ་མཚན་མོ་དེབ་ཀློག་གི་འདུག",
        "text": "She is reading a book at night."
      }
    ]
  },
  {
    "vocab_index": 397,
    "word": "སྤྲིན་པ",
    "gloss": "Cloud",
    "sentences": [
      {
        "target": "ནམ་མཁའ་ལ་སྤྲིན་པ་དཀར་པོ་འདུག",
        "text": "There are white clouds in the sky."
      },
      {
        "target": "སྤྲིན་པ་མང་པོ་ཡོད་ན་ཆར་པ་འབབ་ཀྱི་རེད།",
        "text": "If there are many clouds, it will rain."
      },
      {
        "target": "རིའི་རྩེ་ལ་སྤྲིན་པ་འཁོར་འདུག",
        "text": "Clouds are around the mountain top."
      }
    ]
  },
  {
    "vocab_index": 398,
    "word": "ལྷགས་པ",
    "gloss": "Wind",
    "sentences": [
      {
        "target": "དེ་རིང་ལྷགས་པ་ཆེན་པོ་འདུག",
        "text": "There is a strong wind today."
      },
      {
        "target": "ལྷགས་པ་ཡིས་ལོ་མ་ས་ལ་ཟག་སོང་།",
        "text": "The wind made the leaves fall to the ground."
      },
      {
        "target": "ཁོས་ལྷགས་པ་ནང་ལ་སྒོ་བརྒྱབ།",
        "text": "He closed the door in the wind."
      }
    ]
  },
  {
    "vocab_index": 399,
    "word": "ལོ་མ",
    "gloss": "Leaf",
    "sentences": [
      {
        "target": "ཤིང་གི་ལོ་མ་སྔོན་པོ་རེད།",
        "text": "The tree's leaves are green."
      },
      {
        "target": "སྟོན་ཀ་ལ་ལོ་མ་སེར་པོ་ཆགས།",
        "text": "In autumn, the leaves become yellow."
      },
      {
        "target": "བུ་ཆུང་གིས་ལོ་མ་གཅིག་འཐུས།",
        "text": "The child picked up one leaf."
      }
    ]
  },
  {
    "vocab_index": 400,
    "word": "འབྲུག་སྐད་རྒྱག",
    "gloss": "To thunder",
    "sentences": [
      {
        "target": "ཕྱི་ལ་འབྲུག་སྐད་རྒྱག་གི་འདུག",
        "text": "It is thundering outside."
      },
      {
        "target": "མཚན་མོ་འབྲུག་སྐད་རྒྱག་ནས་ང་གཉིད་མ་ཁུག",
        "text": "It thundered at night, so I could not sleep."
      },
      {
        "target": "ཆར་པ་མ་འབབ་གོང་འབྲུག་སྐད་རྒྱག་སོང་།",
        "text": "Before the rain fell, it thundered."
      }
    ]
  },
  {
    "vocab_index": 401,
    "word": "ས་ཡོམ་རྒྱག",
    "gloss": "To happen an earthquake",
    "sentences": [
      {
        "target": "ཞོགས་པ་ས་ཡོམ་རྒྱག་སོང་།",
        "text": "There was an earthquake in the morning."
      },
      {
        "target": "ས་ཡོམ་རྒྱག་དུས་མི་ཚོ་ཕྱི་ལ་ཕྱིན།",
        "text": "When the earthquake happened, people went outside."
      },
      {
        "target": "དེ་རིང་ས་ཡོམ་རྒྱག་མ་སོང་།",
        "text": "There was no earthquake today."
      }
    ]
  },
  {
    "vocab_index": 402,
    "word": "སྡུག་ཆག",
    "gloss": "Bad",
    "sentences": [
      {
        "target": "དེ་རིང་གནམ་གཤིས་སྡུག་ཆག་རེད།",
        "text": "The weather is bad today."
      },
      {
        "target": "ཁོང་གི་ཁ་ལག་དེ་སྡུག་ཆག་མ་རེད།",
        "text": "His food is not bad."
      },
      {
        "target": "ལམ་དེ་སྡུག་ཆག་ཡིན་ནས་ང་ཚོ་དལ་པོ་ཕྱིན།",
        "text": "The road was bad, so we went slowly."
      }
    ]
  },
  {
    "vocab_index": 403,
    "word": "སེར་བ་འབབ",
    "gloss": "To hail",
    "sentences": [
      {
        "target": "དགོང་དྲོ་སེར་བ་འབབ་སོང་།",
        "text": "It hailed in the evening."
      },
      {
        "target": "སེར་བ་འབབ་ན་མེ་ཏོག་ལ་གནོད།",
        "text": "If it hails, it hurts the flowers."
      },
      {
        "target": "རི་ཁུལ་ལ་སེར་བ་འབབ་ཀྱི་འདུག",
        "text": "It is hailing in the mountain area."
      }
    ]
  },
  {
    "vocab_index": 404,
    "word": "ཆུ་ལོག",
    "gloss": "Flood",
    "sentences": [
      {
        "target": "ཆར་པ་མང་པོ་བབས་ནས་ཆུ་ལོག་བྱུང་།",
        "text": "A lot of rain fell and there was a flood."
      },
      {
        "target": "ཆུ་ལོག་དུས་ལམ་ཁ་བཀག་སོང་།",
        "text": "During the flood, the road was blocked."
      },
      {
        "target": "གྲོང་དེ་ལ་ཆུ་ལོག་གི་ཉེན་ཁ་འདུག",
        "text": "That village has a flood risk."
      }
    ]
  },
  {
    "vocab_index": 405,
    "word": "རླུང་འཚུབ",
    "gloss": "Storm",
    "sentences": [
      {
        "target": "མཚན་མོ་རླུང་འཚུབ་ཆེན་པོ་བྱུང་།",
        "text": "There was a big storm at night."
      },
      {
        "target": "རླུང་འཚུབ་ཡོད་པས་ང་ཚོ་ཁྱིམ་ལ་བསྡད།",
        "text": "Because there was a storm, we stayed home."
      },
      {
        "target": "རླུང་འཚུབ་རྗེས་ལ་ནམ་མཁའ་གཙང་མ་ཆགས།",
        "text": "After the storm, the sky became clear."
      }
    ]
  },
  {
    "vocab_index": 406,
    "word": "འབྲུག་སྐད",
    "gloss": "Thunder",
    "sentences": [
      {
        "target": "འབྲུག་སྐད་ཆེན་པོ་གོ་སོང་།",
        "text": "I heard loud thunder."
      },
      {
        "target": "བུ་ཆུང་འབྲུག་སྐད་ལ་ཞེད་སོང་།",
        "text": "The child was afraid of the thunder."
      },
      {
        "target": "ཆར་པའི་སྐབས་འབྲུག་སྐད་འདུག",
        "text": "There is thunder during the rain."
      }
    ]
  },
  {
    "vocab_index": 407,
    "word": "ཆར་པ་སིམ་སིམ",
    "gloss": "Soft rain",
    "sentences": [
      {
        "target": "ཞོགས་པ་ཆར་པ་སིམ་སིམ་འབབ་ཀྱི་འདུག",
        "text": "A soft rain is falling in the morning."
      },
      {
        "target": "ཆར་པ་སིམ་སིམ་ནང་ལ་ང་འཆམ་འཆམ་ཕྱིན།",
        "text": "I went for a walk in the soft rain."
      },
      {
        "target": "ཆར་པ་སིམ་སིམ་གྱིས་ས་ཆ་དྲོ་པོ་ཆགས།",
        "text": "The soft rain made the place feel gentle and warm."
      }
    ]
  },
  {
    "vocab_index": 408,
    "word": "དྲོ་པོ",
    "gloss": "Warm",
    "sentences": [
      {
        "target": "ཁང་པའི་ནང་དྲོ་པོ་འདུག",
        "text": "It is warm inside the house."
      },
      {
        "target": "ཇ་དྲོ་པོ་འཐུང་དང་།",
        "text": "Drink some warm tea."
      },
      {
        "target": "ཉི་མ་ཤར་ནས་ས་ཆ་དྲོ་པོ་ཆགས།",
        "text": "After the sun rose, the place became warm."
      }
    ]
  },
  {
    "vocab_index": 409,
    "word": "འགྱུར་བ",
    "gloss": "To change",
    "sentences": [
      {
        "target": "གནམ་གཤིས་མགྱོགས་པོ་འགྱུར་བ་རེད།",
        "text": "The weather changes quickly."
      },
      {
        "target": "ཁོང་གི་འཆར་གཞི་འགྱུར་བ་མ་རེད།",
        "text": "His plan did not change."
      },
      {
        "target": "ཚ་གྲང་འགྱུར་བ་ཡིན་ན་གོས་འཁྱེར།",
        "text": "If the temperature changes, bring clothes."
      }
    ]
  },
  {
    "vocab_index": 410,
    "word": "སྨུག་པ",
    "gloss": "Fog",
    "sentences": [
      {
        "target": "ཞོགས་པ་སྨུག་པ་མང་པོ་འདུག",
        "text": "There is a lot of fog in the morning."
      },
      {
        "target": "སྨུག་པ་ནང་ལ་ལམ་མཐོང་དཀའ།",
        "text": "In the fog, it is hard to see the road."
      },
      {
        "target": "ཉི་མ་ཤར་ནས་སྨུག་པ་ཡལ་སོང་།",
        "text": "After the sun rose, the fog disappeared."
      }
    ]
  },
  {
    "vocab_index": 411,
    "word": "མཁའ་རླུང",
    "gloss": "Air, atmosphere",
    "sentences": [
      {
        "target": "རི་ལ་མཁའ་རླུང་གཙང་མ་འདུག",
        "text": "The air in the mountains is clean."
      },
      {
        "target": "ཁང་པའི་ནང་མཁའ་རླུང་གསར་པ་དགོས།",
        "text": "The room needs fresh air."
      },
      {
        "target": "སྤོས་ཀྱི་དྲི་མས་མཁའ་རླུང་ཞིམ་པོ་ཆགས།",
        "text": "The smell of incense made the air pleasant."
      }
    ]
  },
  {
    "vocab_index": 412,
    "word": "ཚ་གྲང",
    "gloss": "Temperature",
    "sentences": [
      {
        "target": "དེ་རིང་ཚ་གྲང་ག་ཚོད་རེད།",
        "text": "What is the temperature today?"
      },
      {
        "target": "རི་ལ་ཚ་གྲང་དམའ་པོ་རེད།",
        "text": "The temperature is low in the mountains."
      },
      {
        "target": "ཚ་གྲང་མཐོ་པོ་ཡིན་ན་ཆུ་མང་པོ་འཐུང་།",
        "text": "If the temperature is high, drink a lot of water."
      }
    ]
  },
  {
    "vocab_index": 413,
    "word": "ན",
    "gloss": "If",
    "sentences": [
      {
        "target": "ཆར་པ་འབབ་ན་ང་ཁྱིམ་ལ་སྡོད།",
        "text": "If it rains, I stay at home."
      },
      {
        "target": "ཁྱེད་རང་ཐང་ཆད་ན་ངལ་གསོ་བྱེད།",
        "text": "If you are tired, rest."
      },
      {
        "target": "དུས་ཚོད་ཡོད་ན་ང་ཚོ་ཐུག",
        "text": "If there is time, we will meet."
      }
    ]
  },
  {
    "vocab_index": 414,
    "word": "མེ་ཏོག",
    "gloss": "Flower",
    "sentences": [
      {
        "target": "མེ་ཏོག་འདི་དམར་པོ་རེད།",
        "text": "This flower is red."
      },
      {
        "target": "ཨ་མས་སྒེའུ་ཁུང་འགྲམ་ལ་མེ་ཏོག་བཞག",
        "text": "Mother put flowers by the window."
      },
      {
        "target": "དཔྱིད་ཀ་མེ་ཏོག་གི་དྲི་མ་ཞིམ་པོ་འདུག",
        "text": "In spring, the flowers smell nice."
      }
    ]
  },
  {
    "vocab_index": 415,
    "word": "ཉེན་ཁ་ཚ་པོ",
    "gloss": "Dangerous",
    "sentences": [
      {
        "target": "ལམ་དེ་ཉེན་ཁ་ཚ་པོ་རེད།",
        "text": "That road is dangerous."
      },
      {
        "target": "ས་ཡོམ་རྒྱག་དུས་ཁང་པ་རྙིང་པ་ཉེན་ཁ་ཚ་པོ་རེད།",
        "text": "During an earthquake, old houses are dangerous."
      },
      {
        "target": "རླུང་འཚུབ་ནང་ལ་ཕྱི་ལ་འགྲོ་བ་ཉེན་ཁ་ཚ་པོ་རེད།",
        "text": "Going outside in a storm is dangerous."
      }
    ]
  },
  {
    "vocab_index": 416,
    "word": "ཤེས",
    "gloss": "To know",
    "sentences": [
      {
        "target": "ངས་ཁོང་གི་མིང་ཤེས།",
        "text": "I know his name."
      },
      {
        "target": "ཁྱེད་རང་བོད་སྐད་ཤེས་ཀྱི་ཡོད་པས།",
        "text": "Do you know Tibetan?"
      },
      {
        "target": "ཁོ་མོས་ལམ་དེ་ཤེས་ཀྱི་མེད།",
        "text": "She does not know that road."
      }
    ]
  },
  {
    "vocab_index": 417,
    "word": "ང་འགྲོ་ཡི་ཡིན",
    "gloss": "I will go",
    "sentences": [
      {
        "target": "སང་ཉིན་ང་འགྲོ་ཡི་ཡིན།",
        "text": "I will go tomorrow."
      },
      {
        "target": "དུས་ཚོད་ཡོད་ན་ང་འགྲོ་ཡི་ཡིན།",
        "text": "If I have time, I will go."
      },
      {
        "target": "ཁྱོད་མ་འགྲོ་ན་ཡང་ང་འགྲོ་ཡི་ཡིན།",
        "text": "Even if you do not go, I will go."
      }
    ]
  },
  {
    "vocab_index": 418,
    "word": "གངས་འབབ་ཀྱི་རེད",
    "gloss": "It will snow",
    "sentences": [
      {
        "target": "སང་ཉིན་རི་ལ་གངས་འབབ་ཀྱི་རེད།",
        "text": "It will snow in the mountains tomorrow."
      },
      {
        "target": "དགོང་མོ་གངས་འབབ་ཀྱི་རེད།",
        "text": "It will snow this evening."
      },
      {
        "target": "གནམ་གཤིས་གྲང་མོ་རེད། གངས་འབབ་ཀྱི་རེད།",
        "text": "The weather is cold. It will snow."
      }
    ]
  },
  {
    "vocab_index": 419,
    "word": "གྲོད་ཁོག་ལྟོགས",
    "gloss": "To be hungry",
    "sentences": [
      {
        "target": "ང་གྲོད་ཁོག་ལྟོགས་ཀྱི་འདུག",
        "text": "I am hungry."
      },
      {
        "target": "ཕྲུ་གུ་གྲོད་ཁོག་ལྟོགས་ནས་ངུས།",
        "text": "The child cried because he was hungry."
      },
      {
        "target": "ཁོ་མོ་གྲོད་ཁོག་ལྟོགས་ན་ཐུག་པ་ཟ།",
        "text": "When she is hungry, she eats noodle soup."
      }
    ]
  },
  {
    "vocab_index": 420,
    "word": "སྨན",
    "gloss": "Medicine, drug",
    "sentences": [
      {
        "target": "ཆམ་པ་ཕོག་ན་སྨན་འཐུང་དགོས།",
        "text": "If you catch a cold, you need to take medicine."
      },
      {
        "target": "ཨ་མས་སྨན་ཁང་ནས་སྨན་ཉོས།",
        "text": "Mother bought medicine from the clinic."
      },
      {
        "target": "ཁོང་ལ་སྨན་དེ་དགོས།",
        "text": "He needs that medicine."
      }
    ]
  },
  {
    "vocab_index": 421,
    "word": "སེར་བ",
    "gloss": "Hail",
    "sentences": [
      {
        "target": "སེར་བ་ཆེན་པོ་ས་ལ་ཟག་སོང་།",
        "text": "Large hail fell to the ground."
      },
      {
        "target": "སེར་བ་རྗེས་ལ་ལམ་དཀར་པོ་ཆགས།",
        "text": "After the hail, the road became white."
      },
      {
        "target": "ཁོས་སེར་བ་ལ་ལྟ་ནས་སྒོ་བརྒྱབ།",
        "text": "He saw the hail and closed the door."
      }
    ]
  },
  {
    "vocab_index": 422,
    "word": "སྒོ",
    "gloss": "Door",
    "sentences": [
      {
        "target": "སྒོ་དེ་ཕྱེ་རོགས།",
        "text": "Please open that door."
      },
      {
        "target": "ལྷགས་པ་ཡོད་པས་སྒོ་བརྒྱབ།",
        "text": "Because there was wind, I closed the door."
      },
      {
        "target": "ཁོ་མོ་སྒོ་འགྲམ་ལ་ལངས་འདུག",
        "text": "She is standing by the door."
      }
    ]
  },
  {
    "vocab_index": 423,
    "word": "སྨུག་པ་འཐིབ",
    "gloss": "To get foggy",
    "sentences": [
      {
        "target": "ཞོགས་པ་ལམ་ལ་སྨུག་པ་འཐིབ་སོང་།",
        "text": "In the morning the road got foggy."
      },
      {
        "target": "སྨུག་པ་འཐིབ་ན་རླངས་འཁོར་དལ་པོ་གཏོང་།",
        "text": "If it gets foggy, drive slowly."
      },
      {
        "target": "རི་མགོ་ལ་སྨུག་པ་འཐིབ་ཀྱི་འདུག",
        "text": "It is getting foggy on the mountain top."
      }
    ]
  },
  {
    "vocab_index": 424,
    "word": "ཚ་གྲང་སྙོམས་པོ",
    "gloss": "Balanced temperature",
    "sentences": [
      {
        "target": "དེ་རིང་ཚ་གྲང་སྙོམས་པོ་འདུག",
        "text": "The temperature is balanced today."
      },
      {
        "target": "ཁང་པའི་ནང་ཚ་གྲང་སྙོམས་པོ་རེད།",
        "text": "Inside the house, the temperature is comfortable."
      },
      {
        "target": "དཔྱིད་ཀ་ཚ་གྲང་སྙོམས་པོ་ཡིན་པས་ང་དགའ།",
        "text": "I like spring because the temperature is balanced."
      }
    ]
  },
  {
    "vocab_index": 425,
    "word": "ཆར་སིམ་སིམ་བབས",
    "gloss": "To rain softly",
    "sentences": [
      {
        "target": "མདང་དགོང་ཆར་སིམ་སིམ་བབས་སོང་།",
        "text": "It rained softly last evening."
      },
      {
        "target": "ཆར་སིམ་སིམ་བབས་ནས་ས་ཆ་གཙང་མ་ཆགས།",
        "text": "It rained softly and the place became clean."
      },
      {
        "target": "ཞོགས་པ་ཆར་སིམ་སིམ་བབས་ཀྱང་ང་འགྲོ་ཡི་ཡིན།",
        "text": "Even if it rains softly in the morning, I will go."
      }
    ]
  },
  {
    "vocab_index": 426,
    "word": "ཁོར་ཡུག",
    "gloss": "Environment, surrounding",
    "sentences": [
      {
        "target": "སློབ་གྲྭའི་ཁོར་ཡུག་གཙང་མ་རེད།",
        "text": "The school environment is clean."
      },
      {
        "target": "ང་ཚོས་ཁོར་ཡུག་ལ་དོ་སྣང་བྱེད།",
        "text": "We care about the environment."
      },
      {
        "target": "རི་ཁུལ་གྱི་ཁོར་ཡུག་ཞི་བདེ་འདུག",
        "text": "The surroundings in the mountain area are peaceful."
      }
    ]
  },
  {
    "vocab_index": 427,
    "word": "ཆམ་པ་ཕོག",
    "gloss": "To catch a cold",
    "sentences": [
      {
        "target": "ཁོ་ལ་ཆམ་པ་ཕོག་སོང་།",
        "text": "He caught a cold."
      },
      {
        "target": "གྲང་མོ་ཡིན་ན་ཆམ་པ་ཕོག་སླ་པོ་རེད།",
        "text": "If it is cold, it is easy to catch a cold."
      },
      {
        "target": "ཆམ་པ་ཕོག་ན་ངལ་གསོ་བྱེད།",
        "text": "If you catch a cold, rest."
      }
    ]
  },
  {
    "vocab_index": 428,
    "word": "ཞེད་སྣང་ཚ་པོ",
    "gloss": "Scary",
    "sentences": [
      {
        "target": "མཚན་མོའི་འབྲུག་སྐད་ཞེད་སྣང་ཚ་པོ་འདུག",
        "text": "The thunder at night is scary."
      },
      {
        "target": "ལམ་རྙིང་པ་དེ་ཞེད་སྣང་ཚ་པོ་རེད།",
        "text": "That old road is scary."
      },
      {
        "target": "གློག་བརྙན་དེ་ཞེད་སྣང་ཚ་པོ་མ་རེད།",
        "text": "That movie is not scary."
      }
    ]
  },
  {
    "vocab_index": 429,
    "word": "ས་ཆ་མང་པོ",
    "gloss": "Many places",
    "sentences": [
      {
        "target": "ངས་བོད་ལ་ས་ཆ་མང་པོ་མཐོང་།",
        "text": "I saw many places in Tibet."
      },
      {
        "target": "ཆར་པས་ས་ཆ་མང་པོ་རློན་པ་ཆགས།",
        "text": "The rain made many places wet."
      },
      {
        "target": "ཁོང་ས་ཆ་མང་པོ་ལ་ཕྱིན་མྱོང་།",
        "text": "He has gone to many places."
      }
    ]
  },
  {
    "vocab_index": 430,
    "word": "ག་པར་ཕྱིན་པ་ཡིན་ནའང",
    "gloss": "Wherever you go",
    "sentences": [
      {
        "target": "ག་པར་ཕྱིན་པ་ཡིན་ནའང་ཆར་གདུགས་འཁྱེར།",
        "text": "Wherever you go, bring an umbrella."
      },
      {
        "target": "ག་པར་ཕྱིན་པ་ཡིན་ནའང་ངས་ཁྱེད་རང་དྲན་གྱི་ཡིན།",
        "text": "Wherever you go, I will remember you."
      },
      {
        "target": "ག་པར་ཕྱིན་པ་ཡིན་ནའང་ཆུ་མང་པོ་འཐུང་།",
        "text": "Wherever you go, drink plenty of water."
      }
    ]
  },
  {
    "vocab_index": 431,
    "word": "རྗེས་མ",
    "gloss": "Afterwards, next",
    "sentences": [
      {
        "target": "རྗེས་མ་ང་ཚོ་ཡང་ཐུག་གི་ཡིན།",
        "text": "Next time we will meet again."
      },
      {
        "target": "ཁ་ལག་ཟས་རྗེས་མ་ང་འཆམ་འཆམ་ཕྱིན།",
        "text": "After eating, I went for a walk."
      },
      {
        "target": "རྗེས་མ་ཁྱེད་རང་སྔ་པོ་ཤོག",
        "text": "Next time, please come early."
      }
    ]
  },
  {
    "vocab_index": 432,
    "word": "སྒྲུང་དེབ",
    "gloss": "Novel, fiction",
    "sentences": [
      {
        "target": "ངས་སྒྲུང་དེབ་གསར་པ་ཀློག་གི་ཡོད།",
        "text": "I am reading a new novel."
      },
      {
        "target": "ཁོ་མོའི་སྒྲུང་དེབ་སྙན་པོ་འདུག",
        "text": "Her novel is interesting."
      },
      {
        "target": "དེབ་ཁང་ལ་སྒྲུང་དེབ་མང་པོ་འདུག",
        "text": "There are many novels in the bookstore."
      }
    ]
  },
  {
    "vocab_index": 433,
    "word": "ཆུ་རྐྱལ",
    "gloss": "Swimming",
    "sentences": [
      {
        "target": "དབྱར་ཁ་ང་ཆུ་རྐྱལ་ལ་དགའ།",
        "text": "In summer, I like swimming."
      },
      {
        "target": "ཁོ་མོས་ཞོགས་པ་ཆུ་རྐྱལ་བྱེད།",
        "text": "She swims in the morning."
      },
      {
        "target": "ཆུ་རྐྱལ་རྗེས་ལ་ཁོ་ཐང་ཆད་སོང་།",
        "text": "After swimming, he got tired."
      }
    ]
  },
  {
    "vocab_index": 434,
    "word": "ཞབས་བྲོ་འཁྲབ",
    "gloss": "To dance",
    "sentences": [
      {
        "target": "ཁོ་མོས་དགོང་དྲོ་ཞབས་བྲོ་འཁྲབ་ཀྱི་འདུག",
        "text": "She is dancing in the evening."
      },
      {
        "target": "ང་ཚོས་དགའ་སྟོན་ལ་ཞབས་བྲོ་འཁྲབ་སོང་།",
        "text": "We danced at the celebration."
      },
      {
        "target": "བུ་མོ་དེ་ཞབས་བྲོ་འཁྲབ་ལ་དགའ།",
        "text": "That girl likes to dance."
      }
    ]
  },
  {
    "vocab_index": 435,
    "word": "རོལ་ཆ",
    "gloss": "Music instrument",
    "sentences": [
      {
        "target": "ཁོང་ལ་རོལ་ཆ་གསར་པ་ཡོད།",
        "text": "He has a new musical instrument."
      },
      {
        "target": "རོལ་ཆ་དེའི་སྒྲ་སྙན་པོ་འདུག",
        "text": "That instrument sounds pleasant."
      },
      {
        "target": "སློབ་གྲྭ་ལ་རོལ་ཆ་མང་པོ་འདུག",
        "text": "There are many musical instruments at school."
      }
    ]
  },
  {
    "vocab_index": 436,
    "word": "གཞས་གཏོང",
    "gloss": "To sing",
    "sentences": [
      {
        "target": "ཁོ་མོས་གཞས་གཏོང་གི་འདུག",
        "text": "She is singing."
      },
      {
        "target": "ང་ཚོས་མཉམ་དུ་གཞས་གཏོང་སོང་།",
        "text": "We sang together."
      },
      {
        "target": "ཕྲུ་གུ་ཚོ་གཞས་གཏོང་ལ་དགའ།",
        "text": "The children like to sing."
      }
    ]
  },
  {
    "vocab_index": 437,
    "word": "རྐང་རྩེད་སྤོ་ལོ",
    "gloss": "Football",
    "sentences": [
      {
        "target": "ཁོ་རྐང་རྩེད་སྤོ་ལོ་ལ་དགའ།",
        "text": "He likes football."
      },
      {
        "target": "སློབ་གྲྭ་རྗེས་ལ་ང་ཚོས་རྐང་རྩེད་སྤོ་ལོ་རྩེ།",
        "text": "After school, we play football."
      },
      {
        "target": "རྐང་རྩེད་སྤོ་ལོ་འགྲན་བསྡུར་དེ་ལྟད་མོ་ཆེན་པོ་རེད།",
        "text": "The football match is exciting to watch."
      }
    ]
  },
  {
    "vocab_index": 438,
    "word": "འགྲན་བསྡུར",
    "gloss": "Match",
    "sentences": [
      {
        "target": "དེ་རིང་འགྲན་བསྡུར་གཅིག་ཡོད།",
        "text": "There is one match today."
      },
      {
        "target": "འགྲན་བསྡུར་རྗེས་ལ་ཁོ་ཐང་ཆད་སོང་།",
        "text": "After the match, he was tired."
      },
      {
        "target": "ངས་འགྲན་བསྡུར་དེ་ལ་ལྟ་གི་ཡིན།",
        "text": "I will watch that match."
      }
    ]
  },
  {
    "vocab_index": 439,
    "word": "གློག་བརྙན",
    "gloss": "Movie",
    "sentences": [
      {
        "target": "ང་དགོང་དྲོ་གློག་བརྙན་ལ་ལྟ་གི་ཡིན།",
        "text": "I will watch a movie this evening."
      },
      {
        "target": "གློག་བརྙན་དེ་སྙན་པོ་འདུག",
        "text": "That movie is interesting."
      },
      {
        "target": "ཁོང་གིས་གློག་བརྙན་གསར་པ་བཟོས།",
        "text": "He made a new movie."
      }
    ]
  },
  {
    "vocab_index": 440,
    "word": "རྟ་རྒྱུག",
    "gloss": "Horse race",
    "sentences": [
      {
        "target": "གྲོང་དེ་ལ་རྟ་རྒྱུག་ཡོད།",
        "text": "There is a horse race in that village."
      },
      {
        "target": "རྟ་རྒྱུག་ལ་མི་མང་པོ་ལྟ་གི་འདུག",
        "text": "Many people are watching the horse race."
      },
      {
        "target": "ངའི་ཨ་ཕ་རྟ་རྒྱུག་ལ་དགའ།",
        "text": "My father likes horse racing."
      }
    ]
  },
  {
    "vocab_index": 441,
    "word": "ཞབས་བྲོ",
    "gloss": "Dance, dancing",
    "sentences": [
      {
        "target": "ཞབས་བྲོ་དེ་ལྟད་མོ་ཆེན་པོ་རེད།",
        "text": "That dance is very nice to watch."
      },
      {
        "target": "ཁོ་མོས་ཞབས་བྲོ་སློབ་ཀྱི་འདུག",
        "text": "She is learning dance."
      },
      {
        "target": "དགའ་སྟོན་ལ་ཞབས་བྲོ་དང་གཞས་ཡོད།",
        "text": "At the celebration there is dancing and song."
      }
    ]
  },
  {
    "vocab_index": 442,
    "word": "ལྟ",
    "gloss": "To look, watch",
    "sentences": [
      {
        "target": "ངས་ནམ་མཁའ་ལ་ལྟ་གི་ཡོད།",
        "text": "I am looking at the sky."
      },
      {
        "target": "ཁོ་མོས་གློག་བརྙན་ལ་ལྟ་སོང་།",
        "text": "She watched a movie."
      },
      {
        "target": "ཁྱེད་རང་སྒོ་འགྲམ་ལ་ལྟ་རོགས།",
        "text": "Please look by the door."
      }
    ]
  },
  {
    "vocab_index": 443,
    "word": "འཆམ་འཆམ་འགྲོ",
    "gloss": "To stroll",
    "sentences": [
      {
        "target": "དགོང་དྲོ་ང་ཚོ་འཆམ་འཆམ་འགྲོ་གི་ཡིན།",
        "text": "This evening we will go for a stroll."
      },
      {
        "target": "གནམ་གཤིས་དྲོ་པོ་ཡིན་ན་ང་འཆམ་འཆམ་འགྲོ་དགའ།",
        "text": "When the weather is warm, I like to stroll."
      },
      {
        "target": "ཁོང་ཚོ་ཆུ་འགྲམ་ལ་འཆམ་འཆམ་འགྲོ་སོང་།",
        "text": "They went for a stroll by the water."
      }
    ]
  },
  {
    "vocab_index": 444,
    "word": "རོལ་ཆ་དཀྲོལ",
    "gloss": "To play music",
    "sentences": [
      {
        "target": "ཁོས་དགོང་དྲོ་རོལ་ཆ་དཀྲོལ་གྱི་འདུག",
        "text": "He is playing music this evening."
      },
      {
        "target": "ངའི་གྲོགས་པོ་རོལ་ཆ་དཀྲོལ་ཤེས།",
        "text": "My friend knows how to play an instrument."
      },
      {
        "target": "ཁོ་མོས་སློབ་གྲྭ་ལ་རོལ་ཆ་དཀྲོལ་སོང་།",
        "text": "She played music at school."
      }
    ]
  },
  {
    "vocab_index": 445,
    "word": "ཉན",
    "gloss": "To listen",
    "sentences": [
      {
        "target": "ངས་རོལ་དབྱངས་ལ་ཉན་གྱི་ཡོད།",
        "text": "I am listening to music."
      },
      {
        "target": "ཁྱེད་རང་དགེ་རྒན་གྱི་སྐད་ལ་ཉན།",
        "text": "Listen to the teacher's voice."
      },
      {
        "target": "ཁོ་མོས་གཞས་སྙན་པོ་ཞིག་ཉན་སོང་།",
        "text": "She listened to a pleasant song."
      }
    ]
  },
  {
    "vocab_index": 446,
    "word": "བོད་པ་ཚོ",
    "gloss": "Tibetans",
    "sentences": [
      {
        "target": "བོད་པ་ཚོ་ཇ་མང་པོ་འཐུང་གི་རེད།",
        "text": "Tibetans drink a lot of tea."
      },
      {
        "target": "དགའ་སྟོན་ལ་བོད་པ་ཚོས་གཞས་གཏོང་།",
        "text": "At the celebration, Tibetans sing."
      },
      {
        "target": "བོད་པ་ཚོ་བོད་སྐད་བཤད་ཀྱི་རེད།",
        "text": "Tibetans speak Tibetan."
      }
    ]
  },
  {
    "vocab_index": 447,
    "word": "རྒྱ་གར་བ",
    "gloss": "Indian",
    "sentences": [
      {
        "target": "ཁོ་རྒྱ་གར་བ་རེད།",
        "text": "He is Indian."
      },
      {
        "target": "ངའི་གྲོགས་མོ་རྒྱ་གར་བ་རེད།",
        "text": "My female friend is Indian."
      },
      {
        "target": "རྒྱ་གར་བ་དེས་བོད་སྐད་ཉུང་ཉུང་ཤེས།",
        "text": "That Indian person knows a little Tibetan."
      }
    ]
  },
  {
    "vocab_index": 448,
    "word": "ཀོ་རི་ཡའི་མི",
    "gloss": "Korean people",
    "sentences": [
      {
        "target": "ཁོ་མོ་ཀོ་རི་ཡའི་མི་རེད།",
        "text": "She is Korean."
      },
      {
        "target": "ཀོ་རི་ཡའི་མི་གཉིས་ཁྲོམ་ལ་འདུག",
        "text": "Two Korean people are at the market."
      },
      {
        "target": "ངས་ཀོ་རི་ཡའི་མི་ཞིག་དང་ཐུག",
        "text": "I met a Korean person."
      }
    ]
  },
  {
    "vocab_index": 449,
    "word": "ཡུ་རོབ་ཀྱི་མི",
    "gloss": "European people",
    "sentences": [
      {
        "target": "ཡུ་རོབ་ཀྱི་མི་ཞིག་ངའི་འཛིན་གྲྭ་ལ་ཡོད།",
        "text": "There is a European person in my class."
      },
      {
        "target": "ཁོང་ཡུ་རོབ་ཀྱི་མི་རེད།",
        "text": "He is European."
      },
      {
        "target": "ཡུ་རོབ་ཀྱི་མི་ཚོས་འགྲེམས་སྟོན་ཁང་ལ་ལྟ་སོང་།",
        "text": "The European people visited the museum."
      }
    ]
  },
  {
    "vocab_index": 450,
    "word": "རྗེས་ལུས་ཐེབས",
    "gloss": "To be late",
    "sentences": [
      {
        "target": "ང་འགྲན་བསྡུར་ལ་རྗེས་ལུས་ཐེབས་སོང་།",
        "text": "I was late for the match."
      },
      {
        "target": "ཁོང་སློབ་ཁྲིད་ལ་རྗེས་ལུས་ཐེབས་མ་སོང་།",
        "text": "He was not late for the lesson."
      },
      {
        "target": "ལམ་ཁ་བཀག་ནས་ང་ཚོ་རྗེས་ལུས་ཐེབས་སོང་།",
        "text": "The road was blocked, so we were late."
      }
    ]
  },
  {
    "vocab_index": 451,
    "word": "ཤ",
    "gloss": "Meat",
    "sentences": [
      {
        "target": "ཁོས་ཤ་ཟ་གི་འདུག",
        "text": "He is eating meat."
      },
      {
        "target": "ང་ཤ་ཉུང་ཉུང་ཟ།",
        "text": "I eat a little meat."
      },
      {
        "target": "ཁ་ལག་ནང་ལ་ཤ་དང་ཚལ་འདུག",
        "text": "There is meat and vegetables in the food."
      }
    ]
  },
  {
    "vocab_index": 452,
    "word": "ལྷོད་ལྷོད་སྡོད",
    "gloss": "To chill",
    "sentences": [
      {
        "target": "གཟའ་མཇུག་ལ་ང་ཁྱིམ་ལ་ལྷོད་ལྷོད་སྡོད་ཀྱི་ཡིན།",
        "text": "On the weekend, I will relax at home."
      },
      {
        "target": "ལས་ཀ་རྗེས་ལ་ཁོང་ལྷོད་ལྷོད་སྡོད་ཀྱི་འདུག",
        "text": "After work, he is relaxing."
      },
      {
        "target": "དེ་རིང་ང་ཚོ་ལྷོད་ལྷོད་སྡོད་དགོས།",
        "text": "Today we need to take it easy."
      }
    ]
  },
  {
    "vocab_index": 453,
    "word": "ཐ་མག་འཐེན",
    "gloss": "To smoke",
    "sentences": [
      {
        "target": "ཁོང་ཐ་མག་འཐེན་གྱི་མི་འདུག",
        "text": "He does not smoke."
      },
      {
        "target": "ཁང་པའི་ནང་ཐ་མག་འཐེན་མ་རོགས།",
        "text": "Please do not smoke inside the house."
      },
      {
        "target": "ཐ་མག་འཐེན་ན་མཁའ་རླུང་སྡུག་ཆག་ཆགས།",
        "text": "If someone smokes, the air becomes bad."
      }
    ]
  },
  {
    "vocab_index": 454,
    "word": "ཉི་མ་རྟག་པར",
    "gloss": "Every day",
    "sentences": [
      {
        "target": "ཉི་མ་རྟག་པར་ང་སློབ་སྦྱོང་བྱེད།",
        "text": "Every day I study."
      },
      {
        "target": "ཁོ་ཉི་མ་རྟག་པར་ལུས་རྩལ་རྩེ།",
        "text": "He exercises every day."
      },
      {
        "target": "ཉི་མ་རྟག་པར་ཨ་མས་ཇ་བཟོ།",
        "text": "Every day Mother makes tea."
      }
    ]
  },
  {
    "vocab_index": 455,
    "word": "སེམས་པ་སྐྱིད་པོ",
    "gloss": "Happy",
    "sentences": [
      {
        "target": "དེ་རིང་ང་སེམས་པ་སྐྱིད་པོ་འདུག",
        "text": "I feel happy today."
      },
      {
        "target": "གྲོགས་པོ་དང་ཐུག་ནས་ཁོ་སེམས་པ་སྐྱིད་པོ་ཆགས།",
        "text": "After meeting his friend, he became happy."
      },
      {
        "target": "གཞས་དེ་ཉན་ནས་ཁོ་མོ་སེམས་པ་སྐྱིད་པོ་རེད།",
        "text": "Listening to that song, she is happy."
      }
    ]
  },
  {
    "vocab_index": 456,
    "word": "རོལ་དབྱངས",
    "gloss": "Music",
    "sentences": [
      {
        "target": "ང་རོལ་དབྱངས་ལ་དགའ།",
        "text": "I like music."
      },
      {
        "target": "ཁོ་མོས་རོལ་དབྱངས་སྙན་པོ་ཉན་གྱི་འདུག",
        "text": "She is listening to pleasant music."
      },
      {
        "target": "རོལ་དབྱངས་ཡོད་ན་ཞབས་བྲོ་ལས་སླ་པོ་རེད།",
        "text": "With music, dancing is easy."
      }
    ]
  },
  {
    "vocab_index": 457,
    "word": "རོགས་པ",
    "gloss": "Help",
    "sentences": [
      {
        "target": "ཁྱེད་རང་གིས་ང་ལ་རོགས་པ་བྱེད་རོགས།",
        "text": "Please help me."
      },
      {
        "target": "ཨ་ཕས་ཁོ་ལ་རོགས་པ་བྱས།",
        "text": "Father helped him."
      },
      {
        "target": "ང་ཚོར་དེ་རིང་རོགས་པ་དགོས།",
        "text": "We need help today."
      }
    ]
  },
  {
    "vocab_index": 458,
    "word": "ལག་རྩེད་སྤོ་ལོ",
    "gloss": "Basketball",
    "sentences": [
      {
        "target": "ཁོ་ལག་རྩེད་སྤོ་ལོ་ལ་དགའ།",
        "text": "He likes basketball."
      },
      {
        "target": "ང་ཚོས་དགོང་དྲོ་ལག་རྩེད་སྤོ་ལོ་རྩེ།",
        "text": "We play basketball in the evening."
      },
      {
        "target": "ལག་རྩེད་སྤོ་ལོ་འགྲན་བསྡུར་དེ་མགྱོགས་པོ་རེད།",
        "text": "That basketball match is fast."
      }
    ]
  },
  {
    "vocab_index": 459,
    "word": "ལུས་རྩལ་རྩེ",
    "gloss": "To do physical exercise",
    "sentences": [
      {
        "target": "ང་ཞོགས་པ་ལུས་རྩལ་རྩེ་གི་ཡོད།",
        "text": "I exercise in the morning."
      },
      {
        "target": "ཁོ་ཉི་མ་རྟག་པར་ལུས་རྩལ་རྩེ་གི་རེད།",
        "text": "He exercises every day."
      },
      {
        "target": "ལུས་རྩལ་རྩེ་རྗེས་ལ་ཆུ་འཐུང་།",
        "text": "After exercising, drink water."
      }
    ]
  },
  {
    "vocab_index": 460,
    "word": "གཉིད་ཁུག",
    "gloss": "To fall asleep",
    "sentences": [
      {
        "target": "བུ་ཆུང་མགྱོགས་པོ་གཉིད་ཁུག་སོང་།",
        "text": "The child fell asleep quickly."
      },
      {
        "target": "མཚན་མོ་ང་གཉིད་ཁུག་གི་མི་འདུག",
        "text": "At night I am not falling asleep."
      },
      {
        "target": "རོལ་དབྱངས་ཉན་ནས་ཁོ་མོ་གཉིད་ཁུག་སོང་།",
        "text": "Listening to music, she fell asleep."
      }
    ]
  },
  {
    "vocab_index": 461,
    "word": "ཁོང་ཁྲོ་ལང",
    "gloss": "To be angry",
    "sentences": [
      {
        "target": "ཁོང་ཁྲོ་ལང་མ་རོགས།",
        "text": "Please do not get angry."
      },
      {
        "target": "ཁོ་ཕྱི་པོ་ཆགས་ནས་དགེ་རྒན་ཁོང་ཁྲོ་ལང་སོང་།",
        "text": "He was late, so the teacher got angry."
      },
      {
        "target": "ཕྲུ་གུས་དེབ་བརླགས་ནས་ཨ་མ་ཁོང་ཁྲོ་ལང་སོང་།",
        "text": "The child lost the book, so Mother got angry."
      }
    ]
  },
  {
    "vocab_index": 462,
    "word": "མཚན་ཚོགས",
    "gloss": "Night club",
    "sentences": [
      {
        "target": "གྲོང་ཁྱེར་ལ་མཚན་ཚོགས་གཅིག་འདུག",
        "text": "There is one night club in the city."
      },
      {
        "target": "ཁོང་ཚོ་མཚན་ཚོགས་ལ་ཞབས་བྲོ་འཁྲབ་སོང་།",
        "text": "They danced at the night club."
      },
      {
        "target": "མཚན་ཚོགས་ནང་ལ་རོལ་དབྱངས་ཆེན་པོ་འདུག",
        "text": "There is loud music inside the night club."
      }
    ]
  },
  {
    "vocab_index": 463,
    "word": "སློབ་ཁྲིད་བྱེད",
    "gloss": "To teach",
    "sentences": [
      {
        "target": "དགེ་རྒན་གྱིས་བོད་སྐད་སློབ་ཁྲིད་བྱེད།",
        "text": "The teacher teaches Tibetan."
      },
      {
        "target": "ཁོང་གིས་ཞོགས་པ་འཛིན་གྲྭ་ལ་སློབ་ཁྲིད་བྱེད་ཀྱི་འདུག",
        "text": "He is teaching class in the morning."
      },
      {
        "target": "ཁོ་མོས་ཕྲུ་གུ་ཚོར་རོལ་ཆ་སློབ་ཁྲིད་བྱེད།",
        "text": "She teaches musical instruments to the children."
      }
    ]
  },
  {
    "vocab_index": 464,
    "word": "རྒྱུག་ཤར་གློད",
    "gloss": "To run",
    "sentences": [
      {
        "target": "ཁོ་ཞོགས་པ་རྒྱུག་ཤར་གློད་ཀྱི་འདུག",
        "text": "He is running in the morning."
      },
      {
        "target": "ཕྲུ་གུ་ཚོས་ཐང་ལ་རྒྱུག་ཤར་གློད་སོང་།",
        "text": "The children ran on the field."
      },
      {
        "target": "རྒྱུག་ཤར་གློད་རྗེས་ལ་ང་ལ་རྔུལ་ནག་ཐོན།",
        "text": "After running, I sweated."
      }
    ]
  },
  {
    "vocab_index": 465,
    "word": "རྒྱལ་ཁ་ཐོབ",
    "gloss": "To win",
    "sentences": [
      {
        "target": "ང་ཚོ་འགྲན་བསྡུར་ལ་རྒྱལ་ཁ་ཐོབ་སོང་།",
        "text": "We won the match."
      },
      {
        "target": "ཁོས་རྐང་རྩེད་སྤོ་ལོ་ལ་རྒྱལ་ཁ་ཐོབ།",
        "text": "He won at football."
      },
      {
        "target": "རྒྱལ་ཁ་ཐོབ་ནས་ཁོ་མོ་སེམས་པ་སྐྱིད་པོ་རེད།",
        "text": "After winning, she was happy."
      }
    ]
  },
  {
    "vocab_index": 466,
    "word": "ལྟད་མོ",
    "gloss": "Spectacle, show",
    "sentences": [
      {
        "target": "དེ་རིང་ལྟད་མོ་ཡག་པོ་ཡོད།",
        "text": "There is a good show today."
      },
      {
        "target": "ཁོང་ཚོས་ལྟད་མོ་ལ་ལྟ་སོང་།",
        "text": "They went to watch a show."
      },
      {
        "target": "ལྟད་མོ་རྗེས་ལ་ང་ཚོ་ཁྱིམ་ལ་ལོག",
        "text": "After the show, we returned home."
      }
    ]
  },
  {
    "vocab_index": 467,
    "word": "བོད་སྐད",
    "gloss": "Tibetan language",
    "sentences": [
      {
        "target": "ང་བོད་སྐད་སློབ་སྦྱོང་བྱེད།",
        "text": "I study Tibetan."
      },
      {
        "target": "ཁྱེད་རང་བོད་སྐད་བཤད་ཤེས་སམ།",
        "text": "Can you speak Tibetan?"
      },
      {
        "target": "དགེ་རྒན་གྱིས་བོད་སྐད་སློབ་ཁྲིད་བྱེད།",
        "text": "The teacher teaches Tibetan."
      }
    ]
  },
  {
    "vocab_index": 468,
    "word": "སྤོ་ལོ་རྩེ",
    "gloss": "To play football",
    "sentences": [
      {
        "target": "ཁོ་དགོང་དྲོ་སྤོ་ལོ་རྩེ་གི་འདུག",
        "text": "He is playing football in the evening."
      },
      {
        "target": "ང་ཚོ་ཐང་ལ་སྤོ་ལོ་རྩེ་སོང་།",
        "text": "We played football on the field."
      },
      {
        "target": "ཆར་པ་འབབ་ན་སྤོ་ལོ་རྩེ་མི་ཐུབ།",
        "text": "If it rains, we cannot play football."
      }
    ]
  },
  {
    "vocab_index": 469,
    "word": "འགྲེམས་སྟོན་ཁང",
    "gloss": "Museum",
    "sentences": [
      {
        "target": "ང་ཚོ་འགྲེམས་སྟོན་ཁང་ལ་ཕྱིན།",
        "text": "We went to the museum."
      },
      {
        "target": "འགྲེམས་སྟོན་ཁང་ནང་ལ་རྫས་རྙིང་པ་མང་པོ་འདུག",
        "text": "Inside the museum there are many old objects."
      },
      {
        "target": "སང་ཉིན་སློབ་ཕྲུག་ཚོ་འགྲེམས་སྟོན་ཁང་ལ་འགྲོ་གི་རེད།",
        "text": "Tomorrow the students will go to the museum."
      }
    ]
  },
  {
    "vocab_index": 470,
    "word": "ཤིང་ཏོག་ཁུ་བ",
    "gloss": "Fruit juice",
    "sentences": [
      {
        "target": "ངས་ཤིང་ཏོག་ཁུ་བ་འཐུང་གི་ཡོད།",
        "text": "I am drinking fruit juice."
      },
      {
        "target": "ཁོ་མོས་ཁྲོམ་ནས་ཤིང་ཏོག་ཁུ་བ་ཉོས།",
        "text": "She bought fruit juice at the market."
      },
      {
        "target": "ཤིང་ཏོག་ཁུ་བ་འདི་ཞིམ་པོ་འདུག",
        "text": "This fruit juice is tasty."
      }
    ]
  },
  {
    "vocab_index": 471,
    "word": "རྒྱ་ནག",
    "gloss": "China",
    "sentences": [
      {
        "target": "ཁོང་རྒྱ་ནག་ནས་ཡོང་བ་རེད།",
        "text": "He is from China."
      },
      {
        "target": "ངས་རྒྱ་ནག་གི་གྲོང་ཁྱེར་མང་པོ་མཐོང་།",
        "text": "I saw many cities in China."
      },
      {
        "target": "རྒྱ་ནག་ལ་མི་མང་པོ་ཡོད།",
        "text": "There are many people in China."
      }
    ]
  },
  {
    "vocab_index": 472,
    "word": "སློབ་སྦྱོང་བྱེད",
    "gloss": "To study",
    "sentences": [
      {
        "target": "ང་ཉི་མ་རྟག་པར་བོད་སྐད་སློབ་སྦྱོང་བྱེད།",
        "text": "I study Tibetan every day."
      },
      {
        "target": "ཁོ་མོ་དེབ་ཁང་ལ་སློབ་སྦྱོང་བྱེད་ཀྱི་འདུག",
        "text": "She is studying in the library."
      },
      {
        "target": "དུས་ཚོད་ཡོད་ན་ང་ཚན་རིག་སློབ་སྦྱོང་བྱེད་ཀྱི་ཡིན།",
        "text": "If I have time, I will study science."
      }
    ]
  },
  {
    "vocab_index": 473,
    "word": "འཁྲུད",
    "gloss": "To wash",
    "sentences": [
      {
        "target": "ངས་ལག་པ་འཁྲུད་ཀྱི་ཡོད།",
        "text": "I am washing my hands."
      },
      {
        "target": "ཨ་མས་གོས་འཁྲུད་སོང་།",
        "text": "Mother washed clothes."
      },
      {
        "target": "ཁ་ལག་ཟ་གོང་ལག་པ་འཁྲུད།",
        "text": "Wash your hands before eating."
      }
    ]
  },
  {
    "vocab_index": 474,
    "word": "རྩེད་མོ་རྩེ",
    "gloss": "To play",
    "sentences": [
      {
        "target": "ཕྲུ་གུ་ཚོས་སྒོ་ཕྱི་ལ་རྩེད་མོ་རྩེ་གི་འདུག",
        "text": "The children are playing outside."
      },
      {
        "target": "ང་ཚོ་གཟའ་མཇུག་ལ་རྩེད་མོ་རྩེ་སོང་།",
        "text": "We played on the weekend."
      },
      {
        "target": "སློབ་གྲྭ་རྗེས་ལ་ཁོ་རྩེད་མོ་རྩེ་དགའ།",
        "text": "After school, he likes to play."
      }
    ]
  },
  {
    "vocab_index": 475,
    "word": "སེམས་ཅན",
    "gloss": "Animals",
    "sentences": [
      {
        "target": "རི་ལ་སེམས་ཅན་མང་པོ་འདུག",
        "text": "There are many animals in the mountains."
      },
      {
        "target": "ཕྲུ་གུ་ཚོ་སེམས་ཅན་ལ་དགའ།",
        "text": "The children like animals."
      },
      {
        "target": "སེམས་ཅན་ལ་ཆུ་དང་ཟས་དགོས།",
        "text": "Animals need water and food."
      }
    ]
  },
  {
    "vocab_index": 476,
    "word": "སྙན་པོ",
    "gloss": "Interesting (only for things we hear)",
    "sentences": [
      {
        "target": "གཞས་དེ་སྙན་པོ་འདུག",
        "text": "That song sounds nice."
      },
      {
        "target": "ཁོང་གི་སྒྲུང་སྙན་པོ་རེད།",
        "text": "His story is interesting to hear."
      },
      {
        "target": "རོལ་ཆའི་སྒྲ་སྙན་པོ་གོ་སོང་།",
        "text": "I heard the pleasant sound of an instrument."
      }
    ]
  },
  {
    "vocab_index": 477,
    "word": "ལས་སླ་པོ",
    "gloss": "Easy",
    "sentences": [
      {
        "target": "སྦྱོང་ཚན་འདི་ལས་སླ་པོ་རེད།",
        "text": "This exercise is easy."
      },
      {
        "target": "བོད་སྐད་འདི་ལས་སླ་པོ་མ་རེད།",
        "text": "This Tibetan is not easy."
      },
      {
        "target": "ཁྱེད་རང་རོགས་པ་བྱས་ན་ལས་སླ་པོ་རེད།",
        "text": "If you help, it is easy."
      }
    ]
  },
  {
    "vocab_index": 478,
    "word": "ཚན་རིག",
    "gloss": "Science",
    "sentences": [
      {
        "target": "ང་ཚན་རིག་ལ་དགའ།",
        "text": "I like science."
      },
      {
        "target": "དགེ་རྒན་གྱིས་ཚན་རིག་སློབ་ཁྲིད་བྱེད།",
        "text": "The teacher teaches science."
      },
      {
        "target": "ཚན་རིག་གི་དེབ་དེ་སྙན་པོ་འདུག",
        "text": "That science book is interesting."
      }
    ]
  },
  {
    "vocab_index": 479,
    "word": "དུས་ཚོད་སྟོང་པ",
    "gloss": "Free time",
    "sentences": [
      {
        "target": "དེ་རིང་ང་ལ་དུས་ཚོད་སྟོང་པ་ཡོད།",
        "text": "I have free time today."
      },
      {
        "target": "དུས་ཚོད་སྟོང་པ་ཡོད་ན་ང་གློག་བརྙན་ལ་ལྟ།",
        "text": "If I have free time, I watch a movie."
      },
      {
        "target": "ཁོ་མོའི་དུས་ཚོད་སྟོང་པ་ཉུང་ཉུང་རེད།",
        "text": "She has a little free time."
      }
    ]
  },
  {
    "vocab_index": 480,
    "word": "བཞུ",
    "gloss": "To melt",
    "sentences": [
      {
        "target": "ཉི་མ་ཤར་ནས་གངས་བཞུ་སོང་།",
        "text": "After the sun came out, the snow melted."
      },
      {
        "target": "ཆུ་ཚ་པོ་ནང་ལ་མར་བཞུ་གི་འདུག",
        "text": "The butter is melting in the hot water."
      },
      {
        "target": "གངས་བཞུ་ན་ལམ་རློན་པ་ཆགས།",
        "text": "If the snow melts, the road becomes wet."
      }
    ]
  },
  {
    "vocab_index": 481,
    "word": "སྟབས་བདེ་པོ",
    "gloss": "Simple",
    "sentences": [
      {
        "target": "ལས་ཀ་འདི་སྟབས་བདེ་པོ་རེད།",
        "text": "This work is simple."
      },
      {
        "target": "འཆར་གཞི་སྟབས་བདེ་པོ་ཞིག་བཟོ།",
        "text": "Make a simple plan."
      },
      {
        "target": "སྐད་ཆ་འདི་སྟབས་བདེ་པོ་ཡིན་པས་ངས་ཤེས།",
        "text": "This sentence is simple, so I understand it."
      }
    ]
  },
  {
    "vocab_index": 482,
    "word": "སིལ་མ",
    "gloss": "Small money, coins",
    "sentences": [
      {
        "target": "ངའི་ཁུག་མ་ནང་ལ་སིལ་མ་འདུག",
        "text": "There are coins in my bag."
      },
      {
        "target": "ཁྲོམ་ལ་སིལ་མ་དགོས།",
        "text": "You need small money at the market."
      },
      {
        "target": "ཁོས་སིལ་མ་གསུམ་སྤྲད།",
        "text": "He gave three coins."
      }
    ]
  },
  {
    "vocab_index": 483,
    "word": "ལག་རྟགས",
    "gloss": "Gift",
    "sentences": [
      {
        "target": "ངས་གྲོགས་མོ་ལ་ལག་རྟགས་ཉོས།",
        "text": "I bought a gift for my female friend."
      },
      {
        "target": "ལག་རྟགས་དེ་ཆུང་ཆུང་རེད།",
        "text": "That gift is small."
      },
      {
        "target": "ཨ་མས་ཁོ་ལ་ལག་རྟགས་སྤྲད།",
        "text": "Mother gave him a gift."
      }
    ]
  },
  {
    "vocab_index": 484,
    "word": "ཁམ་བུ",
    "gloss": "Peach",
    "sentences": [
      {
        "target": "ཁམ་བུ་འདི་ཞིམ་པོ་འདུག",
        "text": "This peach is tasty."
      },
      {
        "target": "ཁོ་མོས་ཁྲོམ་ནས་ཁམ་བུ་ཉོས།",
        "text": "She bought peaches at the market."
      },
      {
        "target": "ངས་ཁམ་བུ་གཅིག་ཟས།",
        "text": "I ate one peach."
      }
    ]
  },
  {
    "vocab_index": 485,
    "word": "ངང་ལག",
    "gloss": "Bananas",
    "sentences": [
      {
        "target": "ངང་ལག་སེར་པོ་རེད།",
        "text": "Bananas are yellow."
      },
      {
        "target": "ཕྲུ་གུ་ཚོ་ངང་ལག་ལ་དགའ།",
        "text": "The children like bananas."
      },
      {
        "target": "ཨ་ཕས་ངང་ལག་གསུམ་ཉོས།",
        "text": "Father bought three bananas."
      }
    ]
  },
  {
    "vocab_index": 486,
    "word": "སྤོས",
    "gloss": "Incense",
    "sentences": [
      {
        "target": "ཨ་མས་ཞོགས་པ་སྤོས་སྤར།",
        "text": "Mother lit incense in the morning."
      },
      {
        "target": "སྤོས་ཀྱི་དྲི་མ་ཞིམ་པོ་འདུག",
        "text": "The incense smells pleasant."
      },
      {
        "target": "ཁང་པའི་ནང་ལ་སྤོས་འདུག",
        "text": "There is incense inside the house."
      }
    ]
  },
  {
    "vocab_index": 487,
    "word": "གོང་ཆག",
    "gloss": "To decrease the price",
    "sentences": [
      {
        "target": "ཁམ་བུའི་གོང་ཆག་སོང་།",
        "text": "The price of peaches went down."
      },
      {
        "target": "ཁྲོམ་ལ་ངང་ལག་གོང་ཆག་གི་འདུག",
        "text": "At the market, the price of bananas is going down."
      },
      {
        "target": "གོང་ཆག་ན་ངས་ལག་རྟགས་ཉོ་གི་ཡིན།",
        "text": "If the price goes down, I will buy the gift."
      }
    ]
  },
  {
    "vocab_index": 488,
    "word": "གོང་འཕར",
    "gloss": "To increase the price",
    "sentences": [
      {
        "target": "ཤིང་ཏོག་ཁུ་བའི་གོང་འཕར་སོང་།",
        "text": "The price of fruit juice went up."
      },
      {
        "target": "ཁྲོམ་ལ་ཤའི་གོང་འཕར་གྱི་འདུག",
        "text": "At the market, the price of meat is going up."
      },
      {
        "target": "གོང་འཕར་ན་ང་ཚོས་ཉུང་ཉུང་ཉོ།",
        "text": "If the price goes up, we buy less."
      }
    ]
  },
  {
    "vocab_index": 489,
    "word": "སྒོ་ཕྱེ",
    "gloss": "To open",
    "sentences": [
      {
        "target": "ཁྱེད་རང་སྒོ་ཕྱེ་རོགས།",
        "text": "Please open the door."
      },
      {
        "target": "ཞོགས་པ་ཨ་ཕས་ཚོང་ཁང་གི་སྒོ་ཕྱེ་སོང་།",
        "text": "In the morning, Father opened the shop door."
      },
      {
        "target": "མཁའ་རླུང་གསར་པ་དགོས་ན་སྒོ་ཕྱེ།",
        "text": "If you need fresh air, open the door."
      }
    ]
  },
  {
    "vocab_index": 490,
    "word": "སྒོ་རྒྱག",
    "gloss": "To close",
    "sentences": [
      {
        "target": "ལྷགས་པ་ཆེན་པོ་ཡོད་པས་སྒོ་རྒྱག",
        "text": "Because there is strong wind, close the door."
      },
      {
        "target": "ཁོ་མོས་མཚན་མོ་སྒོ་རྒྱག་སོང་།",
        "text": "She closed the door at night."
      },
      {
        "target": "ཚོང་ཁང་དགོང་དྲོ་སྒོ་རྒྱག་གི་རེད།",
        "text": "The shop closes in the evening."
      }
    ]
  },
  {
    "vocab_index": 491,
    "word": "ཞིམ་ལོད་ལྟ",
    "gloss": "To taste something",
    "sentences": [
      {
        "target": "ཁ་ལག་འདི་ཞིམ་ལོད་ལྟ་རོགས།",
        "text": "Please taste this food."
      },
      {
        "target": "ངས་ཤིང་ཏོག་ཁུ་བ་ཞིམ་ལོད་ལྟ་སོང་།",
        "text": "I tasted the fruit juice."
      },
      {
        "target": "ཁོ་མོས་ཁམ་བུ་ཞིམ་ལོད་ལྟ་ནས་ཉོས།",
        "text": "She tasted the peach and bought it."
      }
    ]
  },
  {
    "vocab_index": 492,
    "word": "ཟག",
    "gloss": "To fall",
    "sentences": [
      {
        "target": "ཤིང་ནས་ལོ་མ་ཟག་སོང་།",
        "text": "Leaves fell from the tree."
      },
      {
        "target": "ཕོར་པ་ས་ལ་ཟག་མ་སོང་།",
        "text": "The bowl did not fall to the ground."
      },
      {
        "target": "ཆུ་སྒོ་འགྲམ་ནས་ཟག་གི་འདུག",
        "text": "Water is dripping near the door."
      }
    ]
  },
  {
    "vocab_index": 493,
    "word": "གཞག",
    "gloss": "To place, to put",
    "sentences": [
      {
        "target": "དེབ་དེ་ཅོག་ཙེ་སྒང་ལ་གཞག་རོགས།",
        "text": "Please put that book on the table."
      },
      {
        "target": "ཨ་མས་མེ་ཏོག་སྒེའུ་ཁུང་འགྲམ་ལ་གཞག་སོང་།",
        "text": "Mother put the flowers by the window."
      },
      {
        "target": "ངས་སྤ་སེ་ཁུག་མ་ནང་ལ་གཞག",
        "text": "I put the ticket in the bag."
      }
    ]
  },
  {
    "vocab_index": 494,
    "word": "རྫོགས",
    "gloss": "To run out",
    "sentences": [
      {
        "target": "ཇ་རྫོགས་སོང་།",
        "text": "The tea ran out."
      },
      {
        "target": "ཚོང་ཁང་ལ་ངང་ལག་རྫོགས་འདུག",
        "text": "The shop is out of bananas."
      },
      {
        "target": "དུས་ཚོད་རྫོགས་ན་ང་ཚོ་འགྲོ",
        "text": "When time runs out, we go."
      }
    ]
  },
  {
    "vocab_index": 495,
    "word": "སྐྱུར་མོ",
    "gloss": "Sour",
    "sentences": [
      {
        "target": "ཤིང་ཏོག་འདི་སྐྱུར་མོ་འདུག",
        "text": "This fruit is sour."
      },
      {
        "target": "ཁམ་བུ་དེ་སྐྱུར་མོ་མ་རེད།",
        "text": "That peach is not sour."
      },
      {
        "target": "ཁོས་ཁུ་བ་སྐྱུར་མོ་ཞིག་འཐུང་།",
        "text": "He drank a sour juice."
      }
    ]
  },
  {
    "vocab_index": 496,
    "word": "བོང་བུ",
    "gloss": "Donkey",
    "sentences": [
      {
        "target": "གྲོང་གི་ལམ་ལ་བོང་བུ་གཅིག་འདུག",
        "text": "There is one donkey on the village road."
      },
      {
        "target": "བོང་བུས་ཁུག་མ་ཆེན་པོ་འཁྱེར།",
        "text": "The donkey carries a big bag."
      },
      {
        "target": "ཕྲུ་གུས་བོང་བུ་ལ་ཆུ་སྤྲད།",
        "text": "The child gave water to the donkey."
      }
    ]
  },
  {
    "vocab_index": 497,
    "word": "འཛིན་ཤོག",
    "gloss": "Invoice",
    "sentences": [
      {
        "target": "ཚོང་པས་ང་ལ་འཛིན་ཤོག་སྤྲད།",
        "text": "The shopkeeper gave me an invoice."
      },
      {
        "target": "འཛིན་ཤོག་དེ་ཁུག་མ་ནང་ལ་གཞག",
        "text": "Put that invoice in the bag."
      },
      {
        "target": "ཁོ་མོས་འཛིན་ཤོག་ལ་ལྟ་གི་འདུག",
        "text": "She is looking at the invoice."
      }
    ]
  },
  {
    "vocab_index": 498,
    "word": "སྤ་སེ",
    "gloss": "Ticket",
    "sentences": [
      {
        "target": "ངས་གློག་བརྙན་གྱི་སྤ་སེ་ཉོས།",
        "text": "I bought a movie ticket."
      },
      {
        "target": "སྤ་སེ་དེ་མ་བརླག",
        "text": "Do not lose that ticket."
      },
      {
        "target": "ཁོ་མོར་འགྲན་བསྡུར་གྱི་སྤ་སེ་ཡོད།",
        "text": "She has a ticket for the match."
      }
    ]
  },
  {
    "vocab_index": 499,
    "word": "འཆར་གཞི",
    "gloss": "Plan",
    "sentences": [
      {
        "target": "ང་ཚོར་སང་ཉིན་གྱི་འཆར་གཞི་ཡོད།",
        "text": "We have a plan for tomorrow."
      },
      {
        "target": "ཁོང་གི་འཆར་གཞི་སྟབས་བདེ་པོ་རེད།",
        "text": "His plan is simple."
      },
      {
        "target": "ཆར་པ་འབབ་ན་འཆར་གཞི་འགྱུར་བ་རེད།",
        "text": "If it rains, the plan will change."
      }
    ]
  },
  {
    "vocab_index": 500,
    "word": "བར་ཆད",
    "gloss": "Obstacle",
    "sentences": [
      {
        "target": "ལམ་ཁ་ལ་བར་ཆད་ཆེན་པོ་འདུག",
        "text": "There is a big obstacle on the road."
      },
      {
        "target": "ཆར་པ་དེ་ང་ཚོའི་འཆར་གཞིའི་བར་ཆད་རེད།",
        "text": "The rain is an obstacle to our plan."
      },
      {
        "target": "བར་ཆད་ཡོད་ཀྱང་ང་ཚོ་མུ་མཐུད་འགྲོ",
        "text": "Even though there is an obstacle, we keep going."
      }
    ]
  }
]
